// class version 52.0 (52)
// access flags 0x21
public class org/la4j/matrix/dense/Basic1DMatrix extends org/la4j/matrix/DenseMatrix  {

  // compiled from: Basic1DMatrix.java

  // access flags 0x1A
  private final static B MATRIX_TAG = 0

  // access flags 0x2
  private [D self

  // access flags 0x1
  public <init>()V
   L0
    LINENUMBER 44 L0
    ALOAD 0
    ICONST_0
    ICONST_0
    INVOKESPECIAL org/la4j/matrix/dense/Basic1DMatrix.<init> (II)V
   L1
    LINENUMBER 45 L1
    RETURN
   L2
    LOCALVARIABLE this Lorg/la4j/matrix/dense/Basic1DMatrix; L0 L2 0
    MAXSTACK = 3
    MAXLOCALS = 1

  // access flags 0x1
  public <init>(II)V
   L0
    LINENUMBER 48 L0
    ALOAD 0
    ILOAD 1
    ILOAD 2
    ILOAD 1
    ILOAD 2
    IMUL
    NEWARRAY T_DOUBLE
    INVOKESPECIAL org/la4j/matrix/dense/Basic1DMatrix.<init> (II[D)V
   L1
    LINENUMBER 49 L1
    RETURN
   L2
    LOCALVARIABLE this Lorg/la4j/matrix/dense/Basic1DMatrix; L0 L2 0
    LOCALVARIABLE rows I L0 L2 1
    LOCALVARIABLE columns I L0 L2 2
    MAXSTACK = 5
    MAXLOCALS = 3

  // access flags 0x1
  public <init>(II[D)V
   L0
    LINENUMBER 52 L0
    ALOAD 0
    ILOAD 1
    ILOAD 2
    INVOKESPECIAL org/la4j/matrix/DenseMatrix.<init> (II)V
   L1
    LINENUMBER 53 L1
    ALOAD 0
    ALOAD 3
    PUTFIELD org/la4j/matrix/dense/Basic1DMatrix.self : [D
   L2
    LINENUMBER 54 L2
    RETURN
   L3
    LOCALVARIABLE this Lorg/la4j/matrix/dense/Basic1DMatrix; L0 L3 0
    LOCALVARIABLE rows I L0 L3 1
    LOCALVARIABLE columns I L0 L3 2
    LOCALVARIABLE array [D L0 L3 3
    MAXSTACK = 3
    MAXLOCALS = 4

  // access flags 0x9
  public static zero(II)Lorg/la4j/matrix/dense/Basic1DMatrix;
   L0
    LINENUMBER 61 L0
    NEW org/la4j/matrix/dense/Basic1DMatrix
    DUP
    ILOAD 0
    ILOAD 1
    INVOKESPECIAL org/la4j/matrix/dense/Basic1DMatrix.<init> (II)V
    ARETURN
   L1
    LOCALVARIABLE rows I L0 L1 0
    LOCALVARIABLE columns I L0 L1 1
    MAXSTACK = 4
    MAXLOCALS = 2

  // access flags 0x9
  public static constant(IID)Lorg/la4j/matrix/dense/Basic1DMatrix;
   L0
    LINENUMBER 68 L0
    ILOAD 0
    ILOAD 1
    IMUL
    NEWARRAY T_DOUBLE
    ASTORE 4
   L1
    LINENUMBER 69 L1
    ALOAD 4
    DLOAD 2
    INVOKESTATIC java/util/Arrays.fill ([DD)V
   L2
    LINENUMBER 71 L2
    NEW org/la4j/matrix/dense/Basic1DMatrix
    DUP
    ILOAD 0
    ILOAD 1
    ALOAD 4
    INVOKESPECIAL org/la4j/matrix/dense/Basic1DMatrix.<init> (II[D)V
    ARETURN
   L3
    LOCALVARIABLE rows I L0 L3 0
    LOCALVARIABLE columns I L0 L3 1
    LOCALVARIABLE constant D L0 L3 2
    LOCALVARIABLE array [D L1 L3 4
    MAXSTACK = 5
    MAXLOCALS = 5

  // access flags 0x9
  public static diagonal(ID)Lorg/la4j/matrix/dense/Basic1DMatrix;
   L0
    LINENUMBER 79 L0
    ILOAD 0
    ILOAD 0
    IMUL
    NEWARRAY T_DOUBLE
    ASTORE 3
   L1
    LINENUMBER 81 L1
    ICONST_0
    ISTORE 4
   L2
   FRAME FULL [I D [D I] []
    ILOAD 4
    ILOAD 0
    IF_ICMPGE L3
   L4
    LINENUMBER 82 L4
    ALOAD 3
    ILOAD 4
    ILOAD 0
    IMUL
    ILOAD 4
    IADD
    DLOAD 1
    DASTORE
   L5
    LINENUMBER 81 L5
    IINC 4 1
    GOTO L2
   L3
    LINENUMBER 85 L3
   FRAME FULL [I D [D I] []
    NEW org/la4j/matrix/dense/Basic1DMatrix
    DUP
    ILOAD 0
    ILOAD 0
    ALOAD 3
    INVOKESPECIAL org/la4j/matrix/dense/Basic1DMatrix.<init> (II[D)V
    ARETURN
   L6
    LOCALVARIABLE i I L2 L3 4
    LOCALVARIABLE size I L0 L6 0
    LOCALVARIABLE diagonal D L0 L6 1
    LOCALVARIABLE array [D L1 L6 3
    MAXSTACK = 5
    MAXLOCALS = 5

  // access flags 0x9
  public static unit(II)Lorg/la4j/matrix/dense/Basic1DMatrix;
   L0
    LINENUMBER 93 L0
    ILOAD 0
    ILOAD 1
    DCONST_1
    INVOKESTATIC org/la4j/matrix/dense/Basic1DMatrix.constant (IID)Lorg/la4j/matrix/dense/Basic1DMatrix;
    ARETURN
   L1
    LOCALVARIABLE rows I L0 L1 0
    LOCALVARIABLE columns I L0 L1 1
    MAXSTACK = 4
    MAXLOCALS = 2

  // access flags 0x9
  public static identity(I)Lorg/la4j/matrix/dense/Basic1DMatrix;
   L0
    LINENUMBER 100 L0
    ILOAD 0
    DCONST_1
    INVOKESTATIC org/la4j/matrix/dense/Basic1DMatrix.diagonal (ID)Lorg/la4j/matrix/dense/Basic1DMatrix;
    ARETURN
   L1
    LOCALVARIABLE size I L0 L1 0
    MAXSTACK = 3
    MAXLOCALS = 1

  // access flags 0x9
  public static random(IILjava/util/Random;)Lorg/la4j/matrix/dense/Basic1DMatrix;
   L0
    LINENUMBER 108 L0
    ILOAD 0
    ILOAD 1
    IMUL
    NEWARRAY T_DOUBLE
    ASTORE 3
   L1
    LINENUMBER 110 L1
    ICONST_0
    ISTORE 4
   L2
   FRAME FULL [I I java/util/Random [D I] []
    ILOAD 4
    ILOAD 0
    ILOAD 1
    IMUL
    IF_ICMPGE L3
   L4
    LINENUMBER 111 L4
    ALOAD 3
    ILOAD 4
    ALOAD 2
    INVOKEVIRTUAL java/util/Random.nextDouble ()D
    DASTORE
   L5
    LINENUMBER 110 L5
    IINC 4 1
    GOTO L2
   L3
    LINENUMBER 114 L3
   FRAME FULL [I I java/util/Random [D I] []
    NEW org/la4j/matrix/dense/Basic1DMatrix
    DUP
    ILOAD 0
    ILOAD 1
    ALOAD 3
    INVOKESPECIAL org/la4j/matrix/dense/Basic1DMatrix.<init> (II[D)V
    ARETURN
   L6
    LOCALVARIABLE i I L2 L3 4
    LOCALVARIABLE rows I L0 L6 0
    LOCALVARIABLE columns I L0 L6 1
    LOCALVARIABLE random Ljava/util/Random; L0 L6 2
    LOCALVARIABLE array [D L1 L6 3
    MAXSTACK = 5
    MAXLOCALS = 5

  // access flags 0x9
  public static randomSymmetric(ILjava/util/Random;)Lorg/la4j/matrix/dense/Basic1DMatrix;
   L0
    LINENUMBER 121 L0
    ILOAD 0
    ILOAD 0
    IMUL
    NEWARRAY T_DOUBLE
    ASTORE 2
   L1
    LINENUMBER 123 L1
    ICONST_0
    ISTORE 3
   L2
   FRAME FULL [I java/util/Random [D I] []
    ILOAD 3
    ILOAD 0
    IF_ICMPGE L3
   L4
    LINENUMBER 124 L4
    ILOAD 3
    ISTORE 4
   L5
   FRAME FULL [I java/util/Random [D I I] []
    ILOAD 4
    ILOAD 0
    IF_ICMPGE L6
   L7
    LINENUMBER 125 L7
    ALOAD 1
    INVOKEVIRTUAL java/util/Random.nextDouble ()D
    DSTORE 5
   L8
    LINENUMBER 126 L8
    ALOAD 2
    ILOAD 3
    ILOAD 0
    IMUL
    ILOAD 4
    IADD
    DLOAD 5
    DASTORE
   L9
    LINENUMBER 127 L9
    ALOAD 2
    ILOAD 4
    ILOAD 0
    IMUL
    ILOAD 3
    IADD
    DLOAD 5
    DASTORE
   L10
    LINENUMBER 124 L10
    IINC 4 1
    GOTO L5
   L6
    LINENUMBER 123 L6
   FRAME FULL [I java/util/Random [D I I] []
    IINC 3 1
    GOTO L2
   L3
    LINENUMBER 131 L3
   FRAME FULL [I java/util/Random [D I] []
    NEW org/la4j/matrix/dense/Basic1DMatrix
    DUP
    ILOAD 0
    ILOAD 0
    ALOAD 2
    INVOKESPECIAL org/la4j/matrix/dense/Basic1DMatrix.<init> (II[D)V
    ARETURN
   L11
    LOCALVARIABLE value D L8 L10 5
    LOCALVARIABLE j I L5 L6 4
    LOCALVARIABLE i I L2 L3 3
    LOCALVARIABLE size I L0 L11 0
    LOCALVARIABLE random Ljava/util/Random; L0 L11 1
    LOCALVARIABLE array [D L1 L11 2
    MAXSTACK = 5
    MAXLOCALS = 7

  // access flags 0x9
  public static from1DArray(II[D)Lorg/la4j/matrix/dense/Basic1DMatrix;
   L0
    LINENUMBER 139 L0
    NEW org/la4j/matrix/dense/Basic1DMatrix
    DUP
    ILOAD 0
    ILOAD 1
    ALOAD 2
    INVOKESPECIAL org/la4j/matrix/dense/Basic1DMatrix.<init> (II[D)V
    ARETURN
   L1
    LOCALVARIABLE rows I L0 L1 0
    LOCALVARIABLE columns I L0 L1 1
    LOCALVARIABLE array [D L0 L1 2
    MAXSTACK = 5
    MAXLOCALS = 3

  // access flags 0x9
  public static from2DArray([[D)Lorg/la4j/matrix/dense/Basic1DMatrix;
   L0
    LINENUMBER 147 L0
    ALOAD 0
    ARRAYLENGTH
    ISTORE 1
   L1
    LINENUMBER 148 L1
    ALOAD 0
    ICONST_0
    AALOAD
    ARRAYLENGTH
    ISTORE 2
   L2
    LINENUMBER 149 L2
    ILOAD 1
    ILOAD 2
    IDIV
    NEWARRAY T_DOUBLE
    ASTORE 3
   L3
    LINENUMBER 151 L3
    ICONST_0
    ISTORE 4
   L4
    LINENUMBER 152 L4
    ICONST_0
    ISTORE 5
   L5
   FRAME FULL [[[D I I [D I I] []
    ILOAD 5
    ILOAD 1
    IF_ICMPGE L6
   L7
    LINENUMBER 153 L7
    ALOAD 0
    ILOAD 5
    AALOAD
    ICONST_0
    ALOAD 3
    ILOAD 4
    ILOAD 2
    INVOKESTATIC java/lang/System.arraycopy (Ljava/lang/Object;ILjava/lang/Object;II)V
   L8
    LINENUMBER 154 L8
    ILOAD 4
    ILOAD 2
    IADD
    ISTORE 4
   L9
    LINENUMBER 152 L9
    IINC 5 1
    GOTO L5
   L6
    LINENUMBER 157 L6
   FRAME FULL [[[D I I [D I I] []
    NEW org/la4j/matrix/dense/Basic1DMatrix
    DUP
    ILOAD 1
    ILOAD 2
    ALOAD 3
    INVOKESPECIAL org/la4j/matrix/dense/Basic1DMatrix.<init> (II[D)V
    ARETURN
   L10
    LOCALVARIABLE i I L5 L6 5
    LOCALVARIABLE array [[D L0 L10 0
    LOCALVARIABLE rows I L1 L10 1
    LOCALVARIABLE columns I L2 L10 2
    LOCALVARIABLE array1D [D L3 L10 3
    LOCALVARIABLE offset I L4 L10 4
    MAXSTACK = 5
    MAXLOCALS = 6

  // access flags 0x9
  public static block(Lorg/la4j/Matrix;Lorg/la4j/Matrix;Lorg/la4j/Matrix;Lorg/la4j/Matrix;)Lorg/la4j/matrix/dense/Basic1DMatrix;
   L0
    LINENUMBER 165 L0
    ALOAD 0
    INVOKEVIRTUAL org/la4j/Matrix.rows ()I
    ALOAD 1
    INVOKEVIRTUAL org/la4j/Matrix.rows ()I
    IF_ICMPNE L1
    ALOAD 0
    INVOKEVIRTUAL org/la4j/Matrix.columns ()I
    ALOAD 2
    INVOKEVIRTUAL org/la4j/Matrix.columns ()I
    IF_ICMPNE L1
    ALOAD 2
   L2
    LINENUMBER 166 L2
    INVOKEVIRTUAL org/la4j/Matrix.rows ()I
    ALOAD 3
    INVOKEVIRTUAL org/la4j/Matrix.rows ()I
    IF_ICMPNE L1
    ALOAD 1
    INVOKEVIRTUAL org/la4j/Matrix.columns ()I
    ALOAD 3
    INVOKEVIRTUAL org/la4j/Matrix.columns ()I
    IF_ICMPEQ L3
   L1
    LINENUMBER 167 L1
   FRAME FULL [org/la4j/Matrix org/la4j/Matrix org/la4j/Matrix org/la4j/Matrix] []
    NEW java/lang/IllegalArgumentException
    DUP
    LDC "Sides of blocks are incompatible!"
    INVOKESPECIAL java/lang/IllegalArgumentException.<init> (Ljava/lang/String;)V
    ATHROW
   L3
    LINENUMBER 170 L3
   FRAME FULL [org/la4j/Matrix org/la4j/Matrix org/la4j/Matrix org/la4j/Matrix] []
    ALOAD 0
    INVOKEVIRTUAL org/la4j/Matrix.rows ()I
    ALOAD 2
    INVOKEVIRTUAL org/la4j/Matrix.rows ()I
    IADD
    ISTORE 4
   L4
    LINENUMBER 171 L4
    ALOAD 0
    INVOKEVIRTUAL org/la4j/Matrix.columns ()I
    ALOAD 1
    INVOKEVIRTUAL org/la4j/Matrix.columns ()I
    IADD
    ISTORE 5
   L5
    LINENUMBER 172 L5
    ILOAD 4
    ILOAD 5
    IMUL
    NEWARRAY T_DOUBLE
    ASTORE 6
   L6
    LINENUMBER 174 L6
    ICONST_0
    ISTORE 7
   L7
   FRAME FULL [org/la4j/Matrix org/la4j/Matrix org/la4j/Matrix org/la4j/Matrix I I [D I] []
    ILOAD 7
    ILOAD 4
    IF_ICMPGE L8
   L9
    LINENUMBER 175 L9
    ICONST_0
    ISTORE 8
   L10
   FRAME FULL [org/la4j/Matrix org/la4j/Matrix org/la4j/Matrix org/la4j/Matrix I I [D I I] []
    ILOAD 8
    ILOAD 5
    IF_ICMPGE L11
   L12
    LINENUMBER 176 L12
    ILOAD 7
    ALOAD 0
    INVOKEVIRTUAL org/la4j/Matrix.rows ()I
    IF_ICMPGE L13
    ILOAD 8
    ALOAD 0
    INVOKEVIRTUAL org/la4j/Matrix.columns ()I
    IF_ICMPGE L13
   L14
    LINENUMBER 177 L14
    ALOAD 6
    ILOAD 7
    ILOAD 4
    IMUL
    ILOAD 8
    IADD
    ALOAD 0
    ILOAD 7
    ILOAD 8
    INVOKEVIRTUAL org/la4j/Matrix.get (II)D
    DASTORE
   L13
    LINENUMBER 179 L13
   FRAME FULL [org/la4j/Matrix org/la4j/Matrix org/la4j/Matrix org/la4j/Matrix I I [D I I] []
    ILOAD 7
    ALOAD 0
    INVOKEVIRTUAL org/la4j/Matrix.rows ()I
    IF_ICMPGE L15
    ILOAD 8
    ALOAD 0
    INVOKEVIRTUAL org/la4j/Matrix.columns ()I
    IF_ICMPLE L15
   L16
    LINENUMBER 180 L16
    ALOAD 6
    ILOAD 7
    ILOAD 4
    IMUL
    ILOAD 8
    IADD
    ALOAD 1
    ILOAD 7
    ILOAD 8
    INVOKEVIRTUAL org/la4j/Matrix.get (II)D
    DASTORE
   L15
    LINENUMBER 182 L15
   FRAME FULL [org/la4j/Matrix org/la4j/Matrix org/la4j/Matrix org/la4j/Matrix I I [D I I] []
    ILOAD 7
    ALOAD 0
    INVOKEVIRTUAL org/la4j/Matrix.rows ()I
    IF_ICMPLE L17
    ILOAD 8
    ALOAD 0
    INVOKEVIRTUAL org/la4j/Matrix.columns ()I
    IF_ICMPGE L17
   L18
    LINENUMBER 183 L18
    ALOAD 6
    ILOAD 7
    ILOAD 4
    IMUL
    ILOAD 8
    IADD
    ALOAD 2
    ILOAD 7
    ILOAD 8
    INVOKEVIRTUAL org/la4j/Matrix.get (II)D
    DASTORE
   L17
    LINENUMBER 185 L17
   FRAME FULL [org/la4j/Matrix org/la4j/Matrix org/la4j/Matrix org/la4j/Matrix I I [D I I] []
    ILOAD 7
    ALOAD 0
    INVOKEVIRTUAL org/la4j/Matrix.rows ()I
    IF_ICMPLE L19
    ILOAD 8
    ALOAD 0
    INVOKEVIRTUAL org/la4j/Matrix.columns ()I
    IF_ICMPLE L19
   L20
    LINENUMBER 186 L20
    ALOAD 6
    ILOAD 7
    ILOAD 4
    IMUL
    ILOAD 8
    IADD
    ALOAD 3
    ILOAD 7
    ILOAD 8
    INVOKEVIRTUAL org/la4j/Matrix.get (II)D
    DASTORE
   L19
    LINENUMBER 175 L19
   FRAME FULL [org/la4j/Matrix org/la4j/Matrix org/la4j/Matrix org/la4j/Matrix I I [D I I] []
    IINC 8 1
    GOTO L10
   L11
    LINENUMBER 174 L11
   FRAME FULL [org/la4j/Matrix org/la4j/Matrix org/la4j/Matrix org/la4j/Matrix I I [D I I] []
    IINC 7 1
    GOTO L7
   L8
    LINENUMBER 191 L8
   FRAME FULL [org/la4j/Matrix org/la4j/Matrix org/la4j/Matrix org/la4j/Matrix I I [D I] []
    NEW org/la4j/matrix/dense/Basic1DMatrix
    DUP
    ILOAD 4
    ILOAD 5
    ALOAD 6
    INVOKESPECIAL org/la4j/matrix/dense/Basic1DMatrix.<init> (II[D)V
    ARETURN
   L21
    LOCALVARIABLE j I L10 L11 8
    LOCALVARIABLE i I L7 L8 7
    LOCALVARIABLE a Lorg/la4j/Matrix; L0 L21 0
    LOCALVARIABLE b Lorg/la4j/Matrix; L0 L21 1
    LOCALVARIABLE c Lorg/la4j/Matrix; L0 L21 2
    LOCALVARIABLE d Lorg/la4j/Matrix; L0 L21 3
    LOCALVARIABLE rows I L4 L21 4
    LOCALVARIABLE columns I L5 L21 5
    LOCALVARIABLE array [D L6 L21 6
    MAXSTACK = 5
    MAXLOCALS = 9

  // access flags 0x9
  public static fromBinary([B)Lorg/la4j/matrix/dense/Basic1DMatrix;
   L0
    LINENUMBER 202 L0
    ALOAD 0
    INVOKESTATIC java/nio/ByteBuffer.wrap ([B)Ljava/nio/ByteBuffer;
    ASTORE 1
   L1
    LINENUMBER 204 L1
    ALOAD 1
    INVOKEVIRTUAL java/nio/ByteBuffer.get ()B
    IFEQ L2
   L3
    LINENUMBER 205 L3
    NEW java/lang/IllegalArgumentException
    DUP
    LDC "Can not decode Basic1DMatrix from the given byte array."
    INVOKESPECIAL java/lang/IllegalArgumentException.<init> (Ljava/lang/String;)V
    ATHROW
   L2
    LINENUMBER 208 L2
   FRAME FULL [[B java/nio/ByteBuffer] []
    ALOAD 1
    INVOKEVIRTUAL java/nio/ByteBuffer.getInt ()I
    ISTORE 2
   L4
    LINENUMBER 209 L4
    ALOAD 1
    INVOKEVIRTUAL java/nio/ByteBuffer.getInt ()I
    ISTORE 3
   L5
    LINENUMBER 210 L5
    ILOAD 2
    ILOAD 3
    IMUL
    ISTORE 4
   L6
    LINENUMBER 211 L6
    ILOAD 4
    NEWARRAY T_DOUBLE
    ASTORE 5
   L7
    LINENUMBER 213 L7
    ICONST_0
    ISTORE 6
   L8
   FRAME FULL [[B java/nio/ByteBuffer I I I [D I] []
    ILOAD 6
    ILOAD 4
    IF_ICMPGE L9
   L10
    LINENUMBER 214 L10
    ALOAD 5
    ILOAD 6
    ALOAD 1
    INVOKEVIRTUAL java/nio/ByteBuffer.getDouble ()D
    DASTORE
   L11
    LINENUMBER 213 L11
    IINC 6 1
    GOTO L8
   L9
    LINENUMBER 217 L9
   FRAME FULL [[B java/nio/ByteBuffer I I I [D I] []
    NEW org/la4j/matrix/dense/Basic1DMatrix
    DUP
    ILOAD 2
    ILOAD 3
    ALOAD 5
    INVOKESPECIAL org/la4j/matrix/dense/Basic1DMatrix.<init> (II[D)V
    ARETURN
   L12
    LOCALVARIABLE i I L8 L9 6
    LOCALVARIABLE array [B L0 L12 0
    LOCALVARIABLE buffer Ljava/nio/ByteBuffer; L1 L12 1
    LOCALVARIABLE rows I L4 L12 2
    LOCALVARIABLE columns I L5 L12 3
    LOCALVARIABLE capacity I L6 L12 4
    LOCALVARIABLE values [D L7 L12 5
    MAXSTACK = 5
    MAXLOCALS = 7

  // access flags 0x9
  public static fromCSV(Ljava/lang/String;)Lorg/la4j/matrix/dense/Basic1DMatrix;
   L0
    LINENUMBER 228 L0
    ALOAD 0
    INVOKESTATIC org/la4j/Matrix.fromCSV (Ljava/lang/String;)Lorg/la4j/Matrix;
    GETSTATIC org/la4j/Matrices.BASIC_1D : Lorg/la4j/matrix/MatrixFactory;
    INVOKEVIRTUAL org/la4j/Matrix.to (Lorg/la4j/matrix/MatrixFactory;)Lorg/la4j/Matrix;
    CHECKCAST org/la4j/matrix/dense/Basic1DMatrix
    ARETURN
   L1
    LOCALVARIABLE csv Ljava/lang/String; L0 L1 0
    MAXSTACK = 2
    MAXLOCALS = 1

  // access flags 0x9
  public static fromMatrixMarket(Ljava/io/InputStream;)Lorg/la4j/matrix/dense/Basic1DMatrix; throws java/io/IOException 
   L0
    LINENUMBER 240 L0
    ALOAD 0
    INVOKESTATIC org/la4j/Matrix.fromMatrixMarket (Ljava/io/InputStream;)Lorg/la4j/Matrix;
    GETSTATIC org/la4j/Matrices.BASIC_1D : Lorg/la4j/matrix/MatrixFactory;
    INVOKEVIRTUAL org/la4j/Matrix.to (Lorg/la4j/matrix/MatrixFactory;)Lorg/la4j/Matrix;
    CHECKCAST org/la4j/matrix/dense/Basic1DMatrix
    ARETURN
   L1
    LOCALVARIABLE is Ljava/io/InputStream; L0 L1 0
    MAXSTACK = 2
    MAXLOCALS = 1

  // access flags 0x1
  public get(II)D
   L0
    LINENUMBER 245 L0
    ALOAD 0
    ILOAD 1
    ILOAD 2
    INVOKEVIRTUAL org/la4j/matrix/dense/Basic1DMatrix.ensureIndexesAreInBounds (II)V
   L1
    LINENUMBER 246 L1
    ALOAD 0
    GETFIELD org/la4j/matrix/dense/Basic1DMatrix.self : [D
    ILOAD 1
    ALOAD 0
    GETFIELD org/la4j/matrix/dense/Basic1DMatrix.columns : I
    IMUL
    ILOAD 2
    IADD
    DALOAD
    DRETURN
   L2
    LOCALVARIABLE this Lorg/la4j/matrix/dense/Basic1DMatrix; L0 L2 0
    LOCALVARIABLE i I L0 L2 1
    LOCALVARIABLE j I L0 L2 2
    MAXSTACK = 3
    MAXLOCALS = 3

  // access flags 0x1
  public set(IID)V
   L0
    LINENUMBER 251 L0
    ALOAD 0
    ILOAD 1
    ILOAD 2
    INVOKEVIRTUAL org/la4j/matrix/dense/Basic1DMatrix.ensureIndexesAreInBounds (II)V
   L1
    LINENUMBER 252 L1
    ALOAD 0
    GETFIELD org/la4j/matrix/dense/Basic1DMatrix.self : [D
    ILOAD 1
    ALOAD 0
    GETFIELD org/la4j/matrix/dense/Basic1DMatrix.columns : I
    IMUL
    ILOAD 2
    IADD
    DLOAD 3
    DASTORE
   L2
    LINENUMBER 253 L2
    RETURN
   L3
    LOCALVARIABLE this Lorg/la4j/matrix/dense/Basic1DMatrix; L0 L3 0
    LOCALVARIABLE i I L0 L3 1
    LOCALVARIABLE j I L0 L3 2
    LOCALVARIABLE value D L0 L3 3
    MAXSTACK = 4
    MAXLOCALS = 5

  // access flags 0x1
  public setAll(D)V
   L0
    LINENUMBER 257 L0
    ALOAD 0
    GETFIELD org/la4j/matrix/dense/Basic1DMatrix.self : [D
    DLOAD 1
    INVOKESTATIC java/util/Arrays.fill ([DD)V
   L1
    LINENUMBER 258 L1
    RETURN
   L2
    LOCALVARIABLE this Lorg/la4j/matrix/dense/Basic1DMatrix; L0 L2 0
    LOCALVARIABLE value D L0 L2 1
    MAXSTACK = 3
    MAXLOCALS = 3

  // access flags 0x1
  public swapRows(II)V
   L0
    LINENUMBER 262 L0
    ILOAD 1
    ILOAD 2
    IF_ICMPEQ L1
   L2
    LINENUMBER 263 L2
    ICONST_0
    ISTORE 3
   L3
   FRAME FULL [org/la4j/matrix/dense/Basic1DMatrix I I I] []
    ILOAD 3
    ALOAD 0
    GETFIELD org/la4j/matrix/dense/Basic1DMatrix.columns : I
    IF_ICMPGE L1
   L4
    LINENUMBER 264 L4
    ALOAD 0
    GETFIELD org/la4j/matrix/dense/Basic1DMatrix.self : [D
    ILOAD 1
    ALOAD 0
    GETFIELD org/la4j/matrix/dense/Basic1DMatrix.columns : I
    IMUL
    ILOAD 3
    IADD
    DALOAD
    DSTORE 4
   L5
    LINENUMBER 265 L5
    ALOAD 0
    GETFIELD org/la4j/matrix/dense/Basic1DMatrix.self : [D
    ILOAD 1
    ALOAD 0
    GETFIELD org/la4j/matrix/dense/Basic1DMatrix.columns : I
    IMUL
    ILOAD 3
    IADD
    ALOAD 0
    GETFIELD org/la4j/matrix/dense/Basic1DMatrix.self : [D
    ILOAD 2
    ALOAD 0
    GETFIELD org/la4j/matrix/dense/Basic1DMatrix.columns : I
    IMUL
    ILOAD 3
    IADD
    DALOAD
    DASTORE
   L6
    LINENUMBER 266 L6
    ALOAD 0
    GETFIELD org/la4j/matrix/dense/Basic1DMatrix.self : [D
    ILOAD 2
    ALOAD 0
    GETFIELD org/la4j/matrix/dense/Basic1DMatrix.columns : I
    IMUL
    ILOAD 3
    IADD
    DLOAD 4
    DASTORE
   L7
    LINENUMBER 263 L7
    IINC 3 1
    GOTO L3
   L1
    LINENUMBER 269 L1
   FRAME FULL [org/la4j/matrix/dense/Basic1DMatrix I I] []
    RETURN
   L8
    LOCALVARIABLE tmp D L5 L7 4
    LOCALVARIABLE k I L3 L1 3
    LOCALVARIABLE this Lorg/la4j/matrix/dense/Basic1DMatrix; L0 L8 0
    LOCALVARIABLE i I L0 L8 1
    LOCALVARIABLE j I L0 L8 2
    MAXSTACK = 5
    MAXLOCALS = 6

  // access flags 0x1
  public swapColumns(II)V
   L0
    LINENUMBER 273 L0
    ILOAD 1
    ILOAD 2
    IF_ICMPEQ L1
   L2
    LINENUMBER 274 L2
    ICONST_0
    ISTORE 3
   L3
   FRAME FULL [org/la4j/matrix/dense/Basic1DMatrix I I I] []
    ILOAD 3
    ALOAD 0
    GETFIELD org/la4j/matrix/dense/Basic1DMatrix.rows : I
    IF_ICMPGE L1
   L4
    LINENUMBER 275 L4
    ALOAD 0
    GETFIELD org/la4j/matrix/dense/Basic1DMatrix.self : [D
    ILOAD 3
    ALOAD 0
    GETFIELD org/la4j/matrix/dense/Basic1DMatrix.columns : I
    IMUL
    ILOAD 1
    IADD
    DALOAD
    DSTORE 4
   L5
    LINENUMBER 276 L5
    ALOAD 0
    GETFIELD org/la4j/matrix/dense/Basic1DMatrix.self : [D
    ILOAD 3
    ALOAD 0
    GETFIELD org/la4j/matrix/dense/Basic1DMatrix.columns : I
    IMUL
    ILOAD 1
    IADD
    ALOAD 0
    GETFIELD org/la4j/matrix/dense/Basic1DMatrix.self : [D
    ILOAD 3
    ALOAD 0
    GETFIELD org/la4j/matrix/dense/Basic1DMatrix.columns : I
    IMUL
    ILOAD 2
    IADD
    DALOAD
    DASTORE
   L6
    LINENUMBER 277 L6
    ALOAD 0
    GETFIELD org/la4j/matrix/dense/Basic1DMatrix.self : [D
    ILOAD 3
    ALOAD 0
    GETFIELD org/la4j/matrix/dense/Basic1DMatrix.columns : I
    IMUL
    ILOAD 2
    IADD
    DLOAD 4
    DASTORE
   L7
    LINENUMBER 274 L7
    IINC 3 1
    GOTO L3
   L1
    LINENUMBER 280 L1
   FRAME FULL [org/la4j/matrix/dense/Basic1DMatrix I I] []
    RETURN
   L8
    LOCALVARIABLE tmp D L5 L7 4
    LOCALVARIABLE k I L3 L1 3
    LOCALVARIABLE this Lorg/la4j/matrix/dense/Basic1DMatrix; L0 L8 0
    LOCALVARIABLE i I L0 L8 1
    LOCALVARIABLE j I L0 L8 2
    MAXSTACK = 5
    MAXLOCALS = 6

  // access flags 0x1
  public getRow(I)Lorg/la4j/Vector;
   L0
    LINENUMBER 284 L0
    ALOAD 0
    GETFIELD org/la4j/matrix/dense/Basic1DMatrix.columns : I
    NEWARRAY T_DOUBLE
    ASTORE 2
   L1
    LINENUMBER 285 L1
    ALOAD 0
    GETFIELD org/la4j/matrix/dense/Basic1DMatrix.self : [D
    ILOAD 1
    ALOAD 0
    GETFIELD org/la4j/matrix/dense/Basic1DMatrix.columns : I
    IMUL
    ALOAD 2
    ICONST_0
    ALOAD 0
    GETFIELD org/la4j/matrix/dense/Basic1DMatrix.columns : I
    INVOKESTATIC java/lang/System.arraycopy (Ljava/lang/Object;ILjava/lang/Object;II)V
   L2
    LINENUMBER 287 L2
    NEW org/la4j/vector/dense/BasicVector
    DUP
    ALOAD 2
    INVOKESPECIAL org/la4j/vector/dense/BasicVector.<init> ([D)V
    ARETURN
   L3
    LOCALVARIABLE this Lorg/la4j/matrix/dense/Basic1DMatrix; L0 L3 0
    LOCALVARIABLE i I L0 L3 1
    LOCALVARIABLE result [D L1 L3 2
    MAXSTACK = 5
    MAXLOCALS = 3

  // access flags 0x1
  public copyOfShape(II)Lorg/la4j/Matrix;
   L0
    LINENUMBER 292 L0
    ALOAD 0
    ILOAD 1
    ILOAD 2
    INVOKEVIRTUAL org/la4j/matrix/dense/Basic1DMatrix.ensureDimensionsAreCorrect (II)V
   L1
    LINENUMBER 294 L1
    ALOAD 0
    GETFIELD org/la4j/matrix/dense/Basic1DMatrix.rows : I
    ILOAD 1
    IF_ICMPGE L2
    ALOAD 0
    GETFIELD org/la4j/matrix/dense/Basic1DMatrix.columns : I
    ILOAD 2
    IF_ICMPNE L2
   L3
    LINENUMBER 295 L3
    ILOAD 1
    ILOAD 2
    IMUL
    NEWARRAY T_DOUBLE
    ASTORE 3
   L4
    LINENUMBER 296 L4
    ALOAD 0
    GETFIELD org/la4j/matrix/dense/Basic1DMatrix.self : [D
    ICONST_0
    ALOAD 3
    ICONST_0
    ALOAD 0
    GETFIELD org/la4j/matrix/dense/Basic1DMatrix.rows : I
    ILOAD 2
    IMUL
    INVOKESTATIC java/lang/System.arraycopy (Ljava/lang/Object;ILjava/lang/Object;II)V
   L5
    LINENUMBER 298 L5
    NEW org/la4j/matrix/dense/Basic1DMatrix
    DUP
    ILOAD 1
    ILOAD 2
    ALOAD 3
    INVOKESPECIAL org/la4j/matrix/dense/Basic1DMatrix.<init> (II[D)V
    ARETURN
   L2
    LINENUMBER 301 L2
   FRAME FULL [org/la4j/matrix/dense/Basic1DMatrix I I] []
    ILOAD 1
    ILOAD 2
    IMUL
    NEWARRAY T_DOUBLE
    ASTORE 3
   L6
    LINENUMBER 303 L6
    ILOAD 2
    ALOAD 0
    GETFIELD org/la4j/matrix/dense/Basic1DMatrix.columns : I
    IF_ICMPGE L7
    ILOAD 2
    GOTO L8
   L7
   FRAME FULL [org/la4j/matrix/dense/Basic1DMatrix I I [D] []
    ALOAD 0
    GETFIELD org/la4j/matrix/dense/Basic1DMatrix.columns : I
   L8
   FRAME FULL [org/la4j/matrix/dense/Basic1DMatrix I I [D] [I]
    ISTORE 4
   L9
    LINENUMBER 304 L9
    ILOAD 1
    ALOAD 0
    GETFIELD org/la4j/matrix/dense/Basic1DMatrix.rows : I
    IF_ICMPGE L10
    ILOAD 1
    GOTO L11
   L10
   FRAME FULL [org/la4j/matrix/dense/Basic1DMatrix I I [D I] []
    ALOAD 0
    GETFIELD org/la4j/matrix/dense/Basic1DMatrix.rows : I
   L11
   FRAME FULL [org/la4j/matrix/dense/Basic1DMatrix I I [D I] [I]
    ISTORE 5
   L12
    LINENUMBER 306 L12
    ICONST_0
    ISTORE 6
   L13
   FRAME FULL [org/la4j/matrix/dense/Basic1DMatrix I I [D I I I] []
    ILOAD 6
    ILOAD 5
    IF_ICMPGE L14
   L15
    LINENUMBER 307 L15
    ALOAD 0
    GETFIELD org/la4j/matrix/dense/Basic1DMatrix.self : [D
    ILOAD 6
    ALOAD 0
    GETFIELD org/la4j/matrix/dense/Basic1DMatrix.columns : I
    IMUL
    ALOAD 3
    ILOAD 6
    ILOAD 2
    IMUL
    ILOAD 4
    INVOKESTATIC java/lang/System.arraycopy (Ljava/lang/Object;ILjava/lang/Object;II)V
   L16
    LINENUMBER 306 L16
    IINC 6 1
    GOTO L13
   L14
    LINENUMBER 311 L14
   FRAME FULL [org/la4j/matrix/dense/Basic1DMatrix I I [D I I I] []
    NEW org/la4j/matrix/dense/Basic1DMatrix
    DUP
    ILOAD 1
    ILOAD 2
    ALOAD 3
    INVOKESPECIAL org/la4j/matrix/dense/Basic1DMatrix.<init> (II[D)V
    ARETURN
   L17
    LOCALVARIABLE $self [D L4 L2 3
    LOCALVARIABLE i I L13 L14 6
    LOCALVARIABLE this Lorg/la4j/matrix/dense/Basic1DMatrix; L0 L17 0
    LOCALVARIABLE rows I L0 L17 1
    LOCALVARIABLE columns I L0 L17 2
    LOCALVARIABLE $self [D L6 L17 3
    LOCALVARIABLE columnSize I L9 L17 4
    LOCALVARIABLE rowSize I L12 L17 5
    MAXSTACK = 6
    MAXLOCALS = 7

  // access flags 0x1
  public toArray()[[D
   L0
    LINENUMBER 317 L0
    ALOAD 0
    GETFIELD org/la4j/matrix/dense/Basic1DMatrix.rows : I
    ALOAD 0
    GETFIELD org/la4j/matrix/dense/Basic1DMatrix.columns : I
    MULTIANEWARRAY [[D 2
    ASTORE 1
   L1
    LINENUMBER 319 L1
    ICONST_0
    ISTORE 2
   L2
    LINENUMBER 320 L2
    ICONST_0
    ISTORE 3
   L3
   FRAME FULL [org/la4j/matrix/dense/Basic1DMatrix [[D I I] []
    ILOAD 3
    ALOAD 0
    GETFIELD org/la4j/matrix/dense/Basic1DMatrix.rows : I
    IF_ICMPGE L4
   L5
    LINENUMBER 321 L5
    ALOAD 0
    GETFIELD org/la4j/matrix/dense/Basic1DMatrix.self : [D
    ILOAD 2
    ALOAD 1
    ILOAD 3
    AALOAD
    ICONST_0
    ALOAD 0
    GETFIELD org/la4j/matrix/dense/Basic1DMatrix.columns : I
    INVOKESTATIC java/lang/System.arraycopy (Ljava/lang/Object;ILjava/lang/Object;II)V
   L6
    LINENUMBER 322 L6
    ILOAD 2
    ALOAD 0
    GETFIELD org/la4j/matrix/dense/Basic1DMatrix.columns : I
    IADD
    ISTORE 2
   L7
    LINENUMBER 320 L7
    IINC 3 1
    GOTO L3
   L4
    LINENUMBER 325 L4
   FRAME FULL [org/la4j/matrix/dense/Basic1DMatrix [[D I I] []
    ALOAD 1
    ARETURN
   L8
    LOCALVARIABLE i I L3 L4 3
    LOCALVARIABLE this Lorg/la4j/matrix/dense/Basic1DMatrix; L0 L8 0
    LOCALVARIABLE result [[D L1 L8 1
    LOCALVARIABLE offset I L2 L8 2
    MAXSTACK = 5
    MAXLOCALS = 4

  // access flags 0x1
  // signature <T:Lorg/la4j/Matrix;>(Lorg/la4j/matrix/MatrixFactory<TT;>;)TT;
  // declaration: T to<T extends org.la4j.Matrix>(org.la4j.matrix.MatrixFactory<T>)
  public to(Lorg/la4j/matrix/MatrixFactory;)Lorg/la4j/Matrix;
   L0
    LINENUMBER 330 L0
    ALOAD 1
    GETFIELD org/la4j/matrix/MatrixFactory.outputClass : Ljava/lang/Class;
    LDC Lorg/la4j/matrix/dense/Basic1DMatrix;.class
    IF_ACMPNE L1
   L2
    LINENUMBER 331 L2
    ALOAD 1
    GETFIELD org/la4j/matrix/MatrixFactory.outputClass : Ljava/lang/Class;
    ALOAD 0
    INVOKEVIRTUAL java/lang/Class.cast (Ljava/lang/Object;)Ljava/lang/Object;
    CHECKCAST org/la4j/Matrix
    ARETURN
   L1
    LINENUMBER 334 L1
   FRAME FULL [org/la4j/matrix/dense/Basic1DMatrix org/la4j/matrix/MatrixFactory] []
    ALOAD 0
    ALOAD 1
    INVOKESPECIAL org/la4j/matrix/DenseMatrix.to (Lorg/la4j/matrix/MatrixFactory;)Lorg/la4j/Matrix;
    ARETURN
   L3
    LOCALVARIABLE this Lorg/la4j/matrix/dense/Basic1DMatrix; L0 L3 0
    LOCALVARIABLE factory Lorg/la4j/matrix/MatrixFactory; L0 L3 1
    // signature Lorg/la4j/matrix/MatrixFactory<TT;>;
    // declaration: org.la4j.matrix.MatrixFactory<T>
    MAXSTACK = 2
    MAXLOCALS = 2

  // access flags 0x1
  public blankOfShape(II)Lorg/la4j/Matrix;
   L0
    LINENUMBER 339 L0
    ILOAD 1
    ILOAD 2
    INVOKESTATIC org/la4j/matrix/dense/Basic1DMatrix.zero (II)Lorg/la4j/matrix/dense/Basic1DMatrix;
    ARETURN
   L1
    LOCALVARIABLE this Lorg/la4j/matrix/dense/Basic1DMatrix; L0 L1 0
    LOCALVARIABLE rows I L0 L1 1
    LOCALVARIABLE columns I L0 L1 2
    MAXSTACK = 2
    MAXLOCALS = 3

  // access flags 0x1
  public toBinary()[B
   L0
    LINENUMBER 344 L0
    BIPUSH 9
    BIPUSH 8
    ALOAD 0
    GETFIELD org/la4j/matrix/dense/Basic1DMatrix.rows : I
    IMUL
    ALOAD 0
    GETFIELD org/la4j/matrix/dense/Basic1DMatrix.columns : I
    IMUL
    IADD
    ISTORE 1
   L1
    LINENUMBER 349 L1
    ILOAD 1
    INVOKESTATIC java/nio/ByteBuffer.allocate (I)Ljava/nio/ByteBuffer;
    ASTORE 2
   L2
    LINENUMBER 351 L2
    ALOAD 2
    ICONST_0
    INVOKEVIRTUAL java/nio/ByteBuffer.put (B)Ljava/nio/ByteBuffer;
    POP
   L3
    LINENUMBER 352 L3
    ALOAD 2
    ALOAD 0
    GETFIELD org/la4j/matrix/dense/Basic1DMatrix.rows : I
    INVOKEVIRTUAL java/nio/ByteBuffer.putInt (I)Ljava/nio/ByteBuffer;
    POP
   L4
    LINENUMBER 353 L4
    ALOAD 2
    ALOAD 0
    GETFIELD org/la4j/matrix/dense/Basic1DMatrix.columns : I
    INVOKEVIRTUAL java/nio/ByteBuffer.putInt (I)Ljava/nio/ByteBuffer;
    POP
   L5
    LINENUMBER 354 L5
    ALOAD 0
    GETFIELD org/la4j/matrix/dense/Basic1DMatrix.self : [D
    ASTORE 3
    ALOAD 3
    ARRAYLENGTH
    ISTORE 4
    ICONST_0
    ISTORE 5
   L6
   FRAME FULL [org/la4j/matrix/dense/Basic1DMatrix I java/nio/ByteBuffer [D I I] []
    ILOAD 5
    ILOAD 4
    IF_ICMPGE L7
    ALOAD 3
    ILOAD 5
    DALOAD
    DSTORE 6
   L8
    LINENUMBER 355 L8
    ALOAD 2
    DLOAD 6
    INVOKEVIRTUAL java/nio/ByteBuffer.putDouble (D)Ljava/nio/ByteBuffer;
    POP
   L9
    LINENUMBER 354 L9
    IINC 5 1
    GOTO L6
   L7
    LINENUMBER 358 L7
   FRAME FULL [org/la4j/matrix/dense/Basic1DMatrix I java/nio/ByteBuffer [D I I] []
    ALOAD 2
    INVOKEVIRTUAL java/nio/ByteBuffer.array ()[B
    ARETURN
   L10
    LOCALVARIABLE value D L8 L9 6
    LOCALVARIABLE this Lorg/la4j/matrix/dense/Basic1DMatrix; L0 L10 0
    LOCALVARIABLE size I L1 L10 1
    LOCALVARIABLE buffer Ljava/nio/ByteBuffer; L2 L10 2
    MAXSTACK = 3
    MAXLOCALS = 8
}

