// class version 52.0 (52)
// access flags 0x21
public class org/la4j/linear/JacobiSolver extends org/la4j/linear/AbstractSolver  implements org/la4j/linear/LinearSystemSolver  {

  // compiled from: JacobiSolver.java

  // access flags 0x1A
  private final static J serialVersionUID = 4071505

  // access flags 0x12
  private final Lorg/la4j/Matrix; aa

  // access flags 0x1
  public <init>(Lorg/la4j/Matrix;)V
   L0
    LINENUMBER 42 L0
    ALOAD 0
    ALOAD 1
    INVOKESPECIAL org/la4j/linear/AbstractSolver.<init> (Lorg/la4j/Matrix;)V
   L1
    LINENUMBER 45 L1
    ALOAD 0
    ALOAD 1
    INVOKEVIRTUAL org/la4j/Matrix.copy ()Lorg/la4j/Matrix;
    PUTFIELD org/la4j/linear/JacobiSolver.aa : Lorg/la4j/Matrix;
   L2
    LINENUMBER 47 L2
    ICONST_0
    ISTORE 2
   L3
   FRAME FULL [org/la4j/linear/JacobiSolver org/la4j/Matrix I] []
    ILOAD 2
    ALOAD 0
    GETFIELD org/la4j/linear/JacobiSolver.aa : Lorg/la4j/Matrix;
    INVOKEVIRTUAL org/la4j/Matrix.rows ()I
    IF_ICMPGE L4
   L5
    LINENUMBER 48 L5
    ALOAD 0
    GETFIELD org/la4j/linear/JacobiSolver.aa : Lorg/la4j/Matrix;
    ILOAD 2
    ILOAD 2
    INVOKEVIRTUAL org/la4j/Matrix.get (II)D
    INVOKESTATIC org/la4j/Matrices.asDivFunction (D)Lorg/la4j/matrix/functor/MatrixFunction;
    ASTORE 3
   L6
    LINENUMBER 49 L6
    ICONST_0
    ISTORE 4
   L7
   FRAME FULL [org/la4j/linear/JacobiSolver org/la4j/Matrix I org/la4j/matrix/functor/MatrixFunction I] []
    ILOAD 4
    ALOAD 0
    GETFIELD org/la4j/linear/JacobiSolver.aa : Lorg/la4j/Matrix;
    INVOKEVIRTUAL org/la4j/Matrix.columns ()I
    IF_ICMPGE L8
   L9
    LINENUMBER 50 L9
    ILOAD 2
    ILOAD 4
    IF_ICMPEQ L10
   L11
    LINENUMBER 51 L11
    ALOAD 0
    GETFIELD org/la4j/linear/JacobiSolver.aa : Lorg/la4j/Matrix;
    ILOAD 2
    ILOAD 4
    ALOAD 3
    INVOKEVIRTUAL org/la4j/Matrix.updateAt (IILorg/la4j/matrix/functor/MatrixFunction;)V
   L10
    LINENUMBER 49 L10
   FRAME FULL [org/la4j/linear/JacobiSolver org/la4j/Matrix I org/la4j/matrix/functor/MatrixFunction I] []
    IINC 4 1
    GOTO L7
   L8
    LINENUMBER 47 L8
   FRAME FULL [org/la4j/linear/JacobiSolver org/la4j/Matrix I org/la4j/matrix/functor/MatrixFunction I] []
    IINC 2 1
    GOTO L3
   L4
    LINENUMBER 55 L4
   FRAME FULL [org/la4j/linear/JacobiSolver org/la4j/Matrix I] []
    RETURN
   L12
    LOCALVARIABLE j I L7 L8 4
    LOCALVARIABLE divider Lorg/la4j/matrix/functor/MatrixFunction; L6 L8 3
    LOCALVARIABLE i I L3 L4 2
    LOCALVARIABLE this Lorg/la4j/linear/JacobiSolver; L0 L12 0
    LOCALVARIABLE a Lorg/la4j/Matrix; L0 L12 1
    MAXSTACK = 4
    MAXLOCALS = 5

  // access flags 0x1
  public solve(Lorg/la4j/Vector;)Lorg/la4j/Vector;
   L0
    LINENUMBER 59 L0
    ALOAD 0
    ALOAD 1
    INVOKEVIRTUAL org/la4j/linear/JacobiSolver.ensureRHSIsCorrect (Lorg/la4j/Vector;)V
   L1
    LINENUMBER 61 L1
    ALOAD 1
    ALOAD 0
    INVOKEVIRTUAL org/la4j/linear/JacobiSolver.unknowns ()I
    INVOKEVIRTUAL org/la4j/Vector.blankOfLength (I)Lorg/la4j/Vector;
    ASTORE 2
   L2
    LINENUMBER 64 L2
   FRAME FULL [org/la4j/linear/JacobiSolver org/la4j/Vector org/la4j/Vector] []
    ALOAD 0
    GETFIELD org/la4j/linear/JacobiSolver.a : Lorg/la4j/Matrix;
    ALOAD 2
    INVOKEVIRTUAL org/la4j/Matrix.multiply (Lorg/la4j/Vector;)Lorg/la4j/Vector;
    ALOAD 1
    INVOKEVIRTUAL org/la4j/Vector.equals (Ljava/lang/Object;)Z
    IFNE L3
   L4
    LINENUMBER 66 L4
    ALOAD 2
    INVOKEVIRTUAL org/la4j/Vector.blank ()Lorg/la4j/Vector;
    ASTORE 3
   L5
    LINENUMBER 68 L5
    ICONST_0
    ISTORE 4
   L6
   FRAME FULL [org/la4j/linear/JacobiSolver org/la4j/Vector org/la4j/Vector org/la4j/Vector I] []
    ILOAD 4
    ALOAD 0
    GETFIELD org/la4j/linear/JacobiSolver.aa : Lorg/la4j/Matrix;
    INVOKEVIRTUAL org/la4j/Matrix.rows ()I
    IF_ICMPGT L7
   L8
    LINENUMBER 70 L8
    ALOAD 1
    ILOAD 4
    INVOKEVIRTUAL org/la4j/Vector.get (I)D
    ALOAD 0
    GETFIELD org/la4j/linear/JacobiSolver.aa : Lorg/la4j/Matrix;
    ILOAD 4
    ILOAD 4
    INVOKEVIRTUAL org/la4j/Matrix.get (II)D
    DDIV
    DSTORE 5
   L9
    LINENUMBER 71 L9
    ICONST_0
    ISTORE 7
   L10
   FRAME FULL [org/la4j/linear/JacobiSolver org/la4j/Vector org/la4j/Vector org/la4j/Vector I D I] []
    ILOAD 7
    ALOAD 0
    GETFIELD org/la4j/linear/JacobiSolver.aa : Lorg/la4j/Matrix;
    INVOKEVIRTUAL org/la4j/Matrix.columns ()I
    IF_ICMPGE L11
   L12
    LINENUMBER 72 L12
    ILOAD 4
    ILOAD 7
    IF_ICMPEQ L13
   L14
    LINENUMBER 73 L14
    DLOAD 5
    ALOAD 0
    GETFIELD org/la4j/linear/JacobiSolver.aa : Lorg/la4j/Matrix;
    ILOAD 4
    ILOAD 7
    INVOKEVIRTUAL org/la4j/Matrix.get (II)D
    ALOAD 2
    ILOAD 7
    INVOKEVIRTUAL org/la4j/Vector.get (I)D
    DMUL
    DSUB
    DSTORE 5
   L13
    LINENUMBER 71 L13
   FRAME FULL [org/la4j/linear/JacobiSolver org/la4j/Vector org/la4j/Vector org/la4j/Vector I D I] []
    IINC 7 1
    GOTO L10
   L11
    LINENUMBER 77 L11
   FRAME FULL [org/la4j/linear/JacobiSolver org/la4j/Vector org/la4j/Vector org/la4j/Vector I D I] []
    ALOAD 3
    ILOAD 4
    DLOAD 5
    INVOKEVIRTUAL org/la4j/Vector.set (ID)V
   L15
    LINENUMBER 68 L15
    IINC 4 1
    GOTO L6
   L7
    LINENUMBER 80 L7
   FRAME FULL [org/la4j/linear/JacobiSolver org/la4j/Vector org/la4j/Vector org/la4j/Vector I] []
    ALOAD 3
    ASTORE 2
   L16
    LINENUMBER 81 L16
    GOTO L2
   L3
    LINENUMBER 83 L3
   FRAME FULL [org/la4j/linear/JacobiSolver org/la4j/Vector org/la4j/Vector] []
    ALOAD 2
    ARETURN
   L17
    LOCALVARIABLE j I L10 L11 7
    LOCALVARIABLE acc D L9 L15 5
    LOCALVARIABLE i I L6 L7 4
    LOCALVARIABLE next Lorg/la4j/Vector; L5 L16 3
    LOCALVARIABLE this Lorg/la4j/linear/JacobiSolver; L0 L17 0
    LOCALVARIABLE b Lorg/la4j/Vector; L0 L17 1
    LOCALVARIABLE current Lorg/la4j/Vector; L2 L17 2
    MAXSTACK = 6
    MAXLOCALS = 8

  // access flags 0x1
  public applicableTo(Lorg/la4j/Matrix;)Z
   L0
    LINENUMBER 88 L0
    ALOAD 1
    GETSTATIC org/la4j/Matrices.DIAGONALLY_DOMINANT_MATRIX : Lorg/la4j/matrix/functor/AdvancedMatrixPredicate;
    INVOKEVIRTUAL org/la4j/Matrix.is (Lorg/la4j/matrix/functor/AdvancedMatrixPredicate;)Z
    IRETURN
   L1
    LOCALVARIABLE this Lorg/la4j/linear/JacobiSolver; L0 L1 0
    LOCALVARIABLE matrix Lorg/la4j/Matrix; L0 L1 1
    MAXSTACK = 2
    MAXLOCALS = 2
}

