// class version 52.0 (52)
// access flags 0x21
public class org/la4j/linear/SweepSolver extends org/la4j/linear/AbstractSolver  implements org/la4j/linear/LinearSystemSolver  {

  // compiled from: SweepSolver.java

  // access flags 0x1A
  private final static J serialVersionUID = 4071505

  // access flags 0x1
  public <init>(Lorg/la4j/Matrix;)V
   L0
    LINENUMBER 39 L0
    ALOAD 0
    ALOAD 1
    INVOKESPECIAL org/la4j/linear/AbstractSolver.<init> (Lorg/la4j/Matrix;)V
   L1
    LINENUMBER 40 L1
    RETURN
   L2
    LOCALVARIABLE this Lorg/la4j/linear/SweepSolver; L0 L2 0
    LOCALVARIABLE a Lorg/la4j/Matrix; L0 L2 1
    MAXSTACK = 2
    MAXLOCALS = 2

  // access flags 0x1
  public solve(Lorg/la4j/Vector;)Lorg/la4j/Vector;
   L0
    LINENUMBER 44 L0
    ALOAD 0
    ALOAD 1
    INVOKEVIRTUAL org/la4j/linear/SweepSolver.ensureRHSIsCorrect (Lorg/la4j/Vector;)V
   L1
    LINENUMBER 47 L1
    ALOAD 0
    GETFIELD org/la4j/linear/SweepSolver.a : Lorg/la4j/Matrix;
    INVOKEVIRTUAL org/la4j/Matrix.copy ()Lorg/la4j/Matrix;
    ASTORE 2
   L2
    LINENUMBER 48 L2
    ALOAD 1
    INVOKEVIRTUAL org/la4j/Vector.copy ()Lorg/la4j/Vector;
    ASTORE 3
   L3
    LINENUMBER 50 L3
    ALOAD 1
    ALOAD 2
    INVOKEVIRTUAL org/la4j/Matrix.columns ()I
    INVOKEVIRTUAL org/la4j/Vector.blankOfLength (I)Lorg/la4j/Vector;
    ASTORE 4
   L4
    LINENUMBER 52 L4
    ICONST_0
    ISTORE 5
   L5
   FRAME FULL [org/la4j/linear/SweepSolver org/la4j/Vector org/la4j/Matrix org/la4j/Vector org/la4j/Vector I] []
    ILOAD 5
    ALOAD 2
    INVOKEVIRTUAL org/la4j/Matrix.rows ()I
    ICONST_1
    ISUB
    IF_ICMPGE L6
   L7
    LINENUMBER 54 L7
    ALOAD 2
    ILOAD 5
    ILOAD 5
    INVOKEVIRTUAL org/la4j/Matrix.get (II)D
    INVOKESTATIC java/lang/Math.abs (D)D
    DSTORE 6
   L8
    LINENUMBER 55 L8
    ILOAD 5
    ISTORE 8
   L9
    LINENUMBER 57 L9
    ILOAD 5
    ICONST_1
    IADD
    ISTORE 9
   L10
   FRAME FULL [org/la4j/linear/SweepSolver org/la4j/Vector org/la4j/Matrix org/la4j/Vector org/la4j/Vector I D I I] []
    ILOAD 9
    ALOAD 2
    INVOKEVIRTUAL org/la4j/Matrix.columns ()I
    IF_ICMPGE L11
   L12
    LINENUMBER 58 L12
    ALOAD 2
    ILOAD 9
    ILOAD 5
    INVOKEVIRTUAL org/la4j/Matrix.get (II)D
    INVOKESTATIC java/lang/Math.abs (D)D
    DSTORE 10
   L13
    LINENUMBER 59 L13
    DLOAD 10
    DLOAD 6
    DCMPL
    IFLE L14
   L15
    LINENUMBER 60 L15
    DLOAD 10
    DSTORE 6
   L16
    LINENUMBER 61 L16
    ILOAD 9
    ISTORE 8
   L14
    LINENUMBER 57 L14
   FRAME FULL [org/la4j/linear/SweepSolver org/la4j/Vector org/la4j/Matrix org/la4j/Vector org/la4j/Vector I D I I D] []
    IINC 9 1
    GOTO L10
   L11
    LINENUMBER 65 L11
   FRAME FULL [org/la4j/linear/SweepSolver org/la4j/Vector org/la4j/Matrix org/la4j/Vector org/la4j/Vector I D I I] []
    ILOAD 8
    ILOAD 5
    IF_ICMPEQ L17
   L18
    LINENUMBER 66 L18
    ALOAD 2
    ILOAD 8
    ILOAD 5
    INVOKEVIRTUAL org/la4j/Matrix.swapRows (II)V
   L19
    LINENUMBER 67 L19
    ALOAD 3
    ILOAD 5
    ILOAD 8
    INVOKEVIRTUAL org/la4j/Vector.swapElements (II)V
   L17
    LINENUMBER 70 L17
   FRAME FULL [org/la4j/linear/SweepSolver org/la4j/Vector org/la4j/Matrix org/la4j/Vector org/la4j/Vector I D I I] []
    ILOAD 5
    ICONST_1
    IADD
    ISTORE 9
   L20
   FRAME FULL [org/la4j/linear/SweepSolver org/la4j/Vector org/la4j/Matrix org/la4j/Vector org/la4j/Vector I D I I] []
    ILOAD 9
    ALOAD 2
    INVOKEVIRTUAL org/la4j/Matrix.columns ()I
    IF_ICMPGE L21
   L22
    LINENUMBER 72 L22
    ALOAD 2
    ILOAD 9
    ILOAD 5
    INVOKEVIRTUAL org/la4j/Matrix.get (II)D
    ALOAD 2
    ILOAD 5
    ILOAD 5
    INVOKEVIRTUAL org/la4j/Matrix.get (II)D
    DDIV
    DSTORE 10
   L23
    LINENUMBER 73 L23
    ILOAD 5
    ISTORE 12
   L24
   FRAME FULL [org/la4j/linear/SweepSolver org/la4j/Vector org/la4j/Matrix org/la4j/Vector org/la4j/Vector I D I I D I] []
    ILOAD 12
    ALOAD 2
    INVOKEVIRTUAL org/la4j/Matrix.columns ()I
    IF_ICMPGE L25
   L26
    LINENUMBER 74 L26
    ALOAD 2
    ILOAD 9
    ILOAD 12
    ALOAD 2
    ILOAD 5
    ILOAD 12
    INVOKEVIRTUAL org/la4j/Matrix.get (II)D
    DLOAD 10
    DMUL
    INVOKESTATIC org/la4j/Matrices.asMinusFunction (D)Lorg/la4j/matrix/functor/MatrixFunction;
    INVOKEVIRTUAL org/la4j/Matrix.updateAt (IILorg/la4j/matrix/functor/MatrixFunction;)V
   L27
    LINENUMBER 73 L27
    IINC 12 1
    GOTO L24
   L25
    LINENUMBER 77 L25
   FRAME FULL [org/la4j/linear/SweepSolver org/la4j/Vector org/la4j/Matrix org/la4j/Vector org/la4j/Vector I D I I D I] []
    ALOAD 3
    ILOAD 9
    ALOAD 3
    ILOAD 5
    INVOKEVIRTUAL org/la4j/Vector.get (I)D
    DLOAD 10
    DMUL
    INVOKESTATIC org/la4j/Vectors.asMinusFunction (D)Lorg/la4j/vector/functor/VectorFunction;
    INVOKEVIRTUAL org/la4j/Vector.updateAt (ILorg/la4j/vector/functor/VectorFunction;)V
   L28
    LINENUMBER 70 L28
    IINC 9 1
    GOTO L20
   L21
    LINENUMBER 52 L21
   FRAME FULL [org/la4j/linear/SweepSolver org/la4j/Vector org/la4j/Matrix org/la4j/Vector org/la4j/Vector I D I I] []
    IINC 5 1
    GOTO L5
   L6
    LINENUMBER 81 L6
   FRAME FULL [org/la4j/linear/SweepSolver org/la4j/Vector org/la4j/Matrix org/la4j/Vector org/la4j/Vector I] []
    ALOAD 2
    INVOKEVIRTUAL org/la4j/Matrix.rows ()I
    ICONST_1
    IADD
    ISTORE 5
   L29
   FRAME FULL [org/la4j/linear/SweepSolver org/la4j/Vector org/la4j/Matrix org/la4j/Vector org/la4j/Vector I] []
    ILOAD 5
    IFLT L30
   L31
    LINENUMBER 83 L31
    DCONST_0
    DSTORE 6
   L32
    LINENUMBER 85 L32
    ILOAD 5
    ICONST_1
    IADD
    ISTORE 8
   L33
   FRAME FULL [org/la4j/linear/SweepSolver org/la4j/Vector org/la4j/Matrix org/la4j/Vector org/la4j/Vector I D I] []
    ILOAD 8
    ALOAD 2
    INVOKEVIRTUAL org/la4j/Matrix.columns ()I
    IF_ICMPGE L34
   L35
    LINENUMBER 86 L35
    DLOAD 6
    ALOAD 2
    ILOAD 5
    ILOAD 8
    INVOKEVIRTUAL org/la4j/Matrix.get (II)D
    ALOAD 4
    ILOAD 8
    INVOKEVIRTUAL org/la4j/Vector.get (I)D
    DMUL
    DADD
    DSTORE 6
   L36
    LINENUMBER 85 L36
    IINC 8 1
    GOTO L33
   L34
    LINENUMBER 89 L34
   FRAME FULL [org/la4j/linear/SweepSolver org/la4j/Vector org/la4j/Matrix org/la4j/Vector org/la4j/Vector I D I] []
    ALOAD 4
    ILOAD 5
    ALOAD 3
    ILOAD 5
    INVOKEVIRTUAL org/la4j/Vector.get (I)D
    DLOAD 6
    DSUB
    ALOAD 2
    ILOAD 5
    ILOAD 5
    INVOKEVIRTUAL org/la4j/Matrix.get (II)D
    DDIV
    INVOKEVIRTUAL org/la4j/Vector.set (ID)V
   L37
    LINENUMBER 81 L37
    IINC 5 -1
    GOTO L29
   L30
    LINENUMBER 92 L30
   FRAME FULL [org/la4j/linear/SweepSolver org/la4j/Vector org/la4j/Matrix org/la4j/Vector org/la4j/Vector I] []
    ALOAD 4
    ARETURN
   L38
    LOCALVARIABLE value D L13 L14 10
    LOCALVARIABLE j I L10 L11 9
    LOCALVARIABLE k I L24 L25 12
    LOCALVARIABLE c D L23 L28 10
    LOCALVARIABLE j I L20 L21 9
    LOCALVARIABLE maxItem D L8 L21 6
    LOCALVARIABLE maxIndex I L9 L21 8
    LOCALVARIABLE i I L5 L6 5
    LOCALVARIABLE j I L33 L34 8
    LOCALVARIABLE acc D L32 L37 6
    LOCALVARIABLE i I L29 L30 5
    LOCALVARIABLE this Lorg/la4j/linear/SweepSolver; L0 L38 0
    LOCALVARIABLE b Lorg/la4j/Vector; L0 L38 1
    LOCALVARIABLE aa Lorg/la4j/Matrix; L2 L38 2
    LOCALVARIABLE bb Lorg/la4j/Vector; L3 L38 3
    LOCALVARIABLE x Lorg/la4j/Vector; L4 L38 4
    MAXSTACK = 7
    MAXLOCALS = 13

  // access flags 0x1
  public applicableTo(Lorg/la4j/Matrix;)Z
   L0
    LINENUMBER 97 L0
    ALOAD 1
    GETSTATIC org/la4j/Matrices.TRIDIAGONAL_MATRIX : Lorg/la4j/matrix/functor/MatrixPredicate;
    INVOKEVIRTUAL org/la4j/Matrix.is (Lorg/la4j/matrix/functor/MatrixPredicate;)Z
    IRETURN
   L1
    LOCALVARIABLE this Lorg/la4j/linear/SweepSolver; L0 L1 0
    LOCALVARIABLE matrix Lorg/la4j/Matrix; L0 L1 1
    MAXSTACK = 2
    MAXLOCALS = 2
}

